damj/__init__.py
damj/damj.py
damj/utils.py
damj-0.1.4.dist-info/LICENSE
damj-0.1.4.dist-info/METADATA
damj-0.1.4.dist-info/WHEEL
damj-0.1.4.dist-info/top_level.txt
damj-0.1.4.dist-info/RECORD
